aio_healthcheck_python/__init__.py
aio_healthcheck_python/main.py
aio_healthcheck_python-0.1.0.dist-info/LICENSE
aio_healthcheck_python-0.1.0.dist-info/METADATA
aio_healthcheck_python-0.1.0.dist-info/WHEEL
aio_healthcheck_python-0.1.0.dist-info/RECORD
