Metadata-Version: 2.1
Name: aio-healthcheck-python
Version: 0.1.0
Summary: A simple healthcheck using aiohttp
License: Apache-2.0
Author: Evgeny Aleshin
Requires-Python: >=3.9,<4.0
Classifier: License :: OSI Approved :: Apache Software License
Classifier: Programming Language :: Python :: 3
Classifier: Programming Language :: Python :: 3.9
Classifier: Programming Language :: Python :: 3.10
Classifier: Programming Language :: Python :: 3.11
Classifier: Programming Language :: Python :: 3.12
Requires-Dist: aiohttp (>=3.9.3,<4.0.0)
